interbase/__init__.py
interbase/blr.py
interbase/ibase.py
interbase/ibcore.py
interbase/schema.py
interbase/services.py
interbase/utils.py
interbase/version.py
interbase/test/README.md
interbase/test/__init__.py
interbase/test/constants.py
interbase/test/core.py
interbase/test/test_arrays.py
interbase/test/test_bugs.py
interbase/test/test_change_views.py
interbase/test/test_charset_conversion.py
interbase/test/test_connection.py
interbase/test/test_create.py
interbase/test/test_cursor.py
interbase/test/test_dbapi20.py
interbase/test/test_distributed_transaction.py
interbase/test/test_encryption.py
interbase/test/test_events.py
interbase/test/test_insert_data.py
interbase/test/test_prepared_statement.py
interbase/test/test_schema.py
interbase/test/test_services.py
interbase/test/test_stored_proc.py
interbase/test/test_stream_blobs.py
interbase/test/test_transaction.py
interbase/test/files/create-test-db-dialect-1.sh
interbase/test/files/create-test-db-dialect-1.sql
interbase/test/files/create-test-db.bat
interbase/test/files/create-test-db.sh
interbase/test/files/create-test-db.sql
interbase/test/files/ibserverCAfile.pem
interbase/test/files/isql.sh
interbase/test/files/cert/3b307515.0
interbase/test/files/cert/ibserverCAfile.pem
interbase-1.0.1.dist-info/METADATA
interbase-1.0.1.dist-info/WHEEL
interbase-1.0.1.dist-info/top_level.txt
interbase-1.0.1.dist-info/RECORD
