Metadata-Version: 2.4
Name: interbase
Version: 1.0.1
Summary: InterBase RDBMS bindings for Python.
Home-page: https://github.com/Embarcadero/InterBasePython
Author: Sriram Balasubramanian
Author-email: sriram.balasubramanian@embarcadero.com
License: BSD
Project-URL: Documentation, https://github.com/Embarcadero/InterBasePython
Project-URL: Source, https://github.com/Embarcadero/InterBasePython
Project-URL: Tracker, https://github.com/Embarcadero/InterBasePython/issues
Classifier: Development Status :: 5 - Production/Stable
Classifier: License :: OSI Approved :: BSD License
Classifier: Operating System :: OS Independent
Classifier: Programming Language :: Python
Classifier: Topic :: Database
Requires-Python: >=3
Provides-Extra: test
Requires-Dist: pytest>=6.2.2; extra == "test"
Provides-Extra: all
Requires-Dist: pytest>=6.2.2; extra == "all"
